nctotdb/__init__.py
nctotdb/data_model.py
nctotdb/grid_mappings.py
nctotdb/paths.py
nctotdb/proxy.py
nctotdb/utils.py
nctotdb/readers/__init__.py
nctotdb/readers/core.py
nctotdb/readers/tiledb.py
nctotdb/readers/zarr.py
nctotdb/writers/__init__.py
nctotdb/writers/core.py
nctotdb/writers/tiledb.py
nctotdb/writers/zarr.py
tiledb_netcdf-0.3.0.dist-info/LICENSE
tiledb_netcdf-0.3.0.dist-info/METADATA
tiledb_netcdf-0.3.0.dist-info/WHEEL
tiledb_netcdf-0.3.0.dist-info/top_level.txt
tiledb_netcdf-0.3.0.dist-info/RECORD
