Metadata-Version: 2.1
Name: tiledb-netcdf
Version: 0.3.0
Summary: An adapter to convert NetCDF files to TileDB or Zarr arrays
Home-page: https://github.com/informatics-lab/tiledb_netcdf
Author: Peter Killick
Author-email: peter.killick@informaticslab.co.uk
License: UNKNOWN
Platform: UNKNOWN
Classifier: Programming Language :: Python :: 3
Classifier: License :: OSI Approved :: GNU General Public License v3 or later (GPLv3+)
Classifier: Operating System :: OS Independent
Requires-Python: >=3.7
Requires-Dist: distributed (>=2.28.0)
Requires-Dist: tiledb (>=0.6.6)
Requires-Dist: scitools-iris (>=2.4.0)
Requires-Dist: xarray (>=0.15.1)
Requires-Dist: zarr (>=2.4.0)
